<annotation>
	<folder>BoTWpics</folder>
	<filename>124ba190-eb68-4fca-a857-2dd28f4890a4.png</filename>
	<path>C:\BoTWpics\124ba190-eb68-4fca-a857-2dd28f4890a4.png</path>
	<source>
		<database>Unknown</database>
	</source>
	<size>
		<width>850</width>
		<height>707</height>
		<depth>3</depth>
	</size>
	<segmented>0</segmented>
	<object>
		<name>dude</name>
		<pose>Unspecified</pose>
		<truncated>0</truncated>
		<difficult>0</difficult>
		<bndbox>
			<xmin>623</xmin>
			<ymin>289</ymin>
			<xmax>670</xmax>
			<ymax>390</ymax>
		</bndbox>
	</object>
	<object>
		<name>link</name>
		<pose>Unspecified</pose>
		<truncated>0</truncated>
		<difficult>0</difficult>
		<bndbox>
			<xmin>362</xmin>
			<ymin>370</ymin>
			<xmax>454</xmax>
			<ymax>523</ymax>
		</bndbox>
	</object>
	<object>
		<name>snowball</name>
		<pose>Unspecified</pose>
		<truncated>0</truncated>
		<difficult>0</difficult>
		<bndbox>
			<xmin>329</xmin>
			<ymin>213</ymin>
			<xmax>513</xmax>
			<ymax>393</ymax>
		</bndbox>
	</object>
</annotation>
